signal_ICT_HARSHAL_92510133020/__init__.py
signal_ICT_HARSHAL_92510133020/operations.py
signal_ICT_HARSHAL_92510133020/trigonometric_signals.py
signal_ICT_HARSHAL_92510133020/unitary_signals.py
signal_ICT_HARSHAL_92510133020/Plots/Cosin wave.png
signal_ICT_HARSHAL_92510133020/Plots/Exponential wave.png
signal_ICT_HARSHAL_92510133020/Plots/Ramp signal.png
signal_ICT_HARSHAL_92510133020/Plots/Signal Addition.png
signal_ICT_HARSHAL_92510133020/Plots/Signal Multiplication.png
signal_ICT_HARSHAL_92510133020/Plots/Sinc Wave.png
signal_ICT_HARSHAL_92510133020/Plots/Time-Scale.png
signal_ICT_HARSHAL_92510133020/Plots/Time-Shifted.png
signal_ICT_HARSHAL_92510133020/Plots/Unit impluse.png
signal_ICT_HARSHAL_92510133020/Plots/Unit step.png
signal_ict_harshal_92510133020-0.0.1.dist-info/METADATA
signal_ict_harshal_92510133020-0.0.1.dist-info/WHEEL
signal_ict_harshal_92510133020-0.0.1.dist-info/RECORD
