Metadata-Version: 2.4
Name: signal_ICT_HARSHAL_92510133020
Version: 0.0.1
Summary: collection of signals of different types
Project-URL: Homepage, https://github.com/Harshalbhatt2806/Python-LHC
Project-URL: Issues, https://github.com/Harshalbhatt2806/Python-LHC
Author-email: Harshal <harshalabhatt@gmail.com>
Classifier: License :: OSI Approved :: GNU General Public License v3 (GPLv3)
Classifier: Operating System :: OS Independent
Classifier: Programming Language :: Python :: 3
Requires-Python: >=3.0
